my_pkg/__init__.py
my_pkg/add.py
point_utils_pxo-0.1.1.dist-info/LICENSE
point_utils_pxo-0.1.1.dist-info/METADATA
point_utils_pxo-0.1.1.dist-info/WHEEL
point_utils_pxo-0.1.1.dist-info/top_level.txt
point_utils_pxo-0.1.1.dist-info/RECORD
