Metadata-Version: 2.1
Name: point-utils-pxo
Version: 0.1.1
Summary: test first package
Home-page: https://gitee.com/leehiking/my_pkg_1
Author: leehiking
Author-email: gz6201347@163.com
Classifier: Programming Language :: Python :: 3
Classifier: License :: OSI Approved :: MIT License
Classifier: Operating System :: OS Independent
License-File: LICENSE
Requires-Dist: torch (>=1.0)
Requires-Dist: numpy (>=1.0)
